agb_star_deprojection_methods/__init__.py
agb_star_deprojection_methods/classes.py
agb_star_deprojection_methods-0.0.3.dist-info/METADATA
agb_star_deprojection_methods-0.0.3.dist-info/WHEEL
agb_star_deprojection_methods-0.0.3.dist-info/licenses/LICENSE
agb_star_deprojection_methods-0.0.3.dist-info/RECORD
