Metadata-Version: 2.4
Name: agb_star_deprojection_methods
Version: 0.0.3
Summary: Package for visualising radially expanding circumstellar envelopes of AGB stars.
Project-URL: Documentation, https://psychedelickoala.github.io/agb-star-deprojection-docs/AGB-Star-Deprojection.html
Author-email: Annalisa Calvi <annalisacalvi@icloud.com>, Jacob Zhang <jzhang27182@gmail.com>
License-Expression: MIT
License-File: LICENSE
Keywords: AGB,AGB stars,astronomy,astrophysics,circumstellar envelope,deprojection,stars,visualisation
Classifier: Operating System :: OS Independent
Classifier: Programming Language :: Python :: 3
Requires-Python: >=3.9
Requires-Dist: astropy==7.1.0
Requires-Dist: matplotlib==3.7.2
Requires-Dist: numpy==1.25.2
Requires-Dist: plotly==6.2.0
Requires-Dist: scipy==1.16.0
